hypothesaes/__init__.py
hypothesaes/annotate.py
hypothesaes/embedding.py
hypothesaes/evaluation.py
hypothesaes/interpret_neurons.py
hypothesaes/llm_api.py
hypothesaes/llm_local.py
hypothesaes/quickstart.py
hypothesaes/sae.py
hypothesaes/select_neurons.py
hypothesaes/utils.py
hypothesaes/prompts/annotate-simple.txt
hypothesaes/prompts/annotate.txt
hypothesaes/prompts/interpret-neuron-binary-reasoning.txt
hypothesaes/prompts/interpret-neuron-binary.txt
hypothesaes/prompts/surface-similarity.txt
hypothesaes-1.0.0.dist-info/licenses/LICENSE
hypothesaes-1.0.0.dist-info/METADATA
hypothesaes-1.0.0.dist-info/WHEEL
hypothesaes-1.0.0.dist-info/top_level.txt
hypothesaes-1.0.0.dist-info/RECORD
