Metadata-Version: 2.4
Name: hypothesaes
Version: 1.0.0
Summary: Hypothesizing interpretable relationships in text datasets using sparse autoencoders.
Author-email: Rajiv Movva <rmovva@berkeley.edu>, Kenny Peng <kennypeng@cs.cornell.edu>
Project-URL: Homepage, https://github.com/rmovva/HypotheSAEs
Project-URL: Bug Tracker, https://github.com/rmovva/HypotheSAEs/issues
Project-URL: Changelog, https://github.com/rmovva/HypotheSAEs/blob/main/CHANGELOG.md
Classifier: Programming Language :: Python :: 3
Classifier: License :: OSI Approved :: MIT License
Classifier: Operating System :: OS Independent
Requires-Python: <3.13,>=3.10
License-File: LICENSE
Requires-Dist: accelerate
Requires-Dist: jupyter
Requires-Dist: matplotlib
Requires-Dist: numpy
Requires-Dist: openai
Requires-Dist: pandas
Requires-Dist: pytest
Requires-Dist: scikit-learn
Requires-Dist: scipy==1.15.3
Requires-Dist: sentence-transformers
Requires-Dist: statsmodels
Requires-Dist: tiktoken
Requires-Dist: torch
Requires-Dist: tqdm
Requires-Dist: transformers
Requires-Dist: vllm
Requires-Dist: jmespath
Dynamic: license-file
